bonaventure_scale/__init__.py
bonaventure_scale/conversions.py
bonaventure_scale-0.1.0.dist-info/licenses/LICENSE
bonaventure_scale-0.1.0.dist-info/METADATA
bonaventure_scale-0.1.0.dist-info/WHEEL
bonaventure_scale-0.1.0.dist-info/top_level.txt
bonaventure_scale-0.1.0.dist-info/RECORD
