Metadata-Version: 2.4
Name: bonaventure_scale
Version: 0.1.0
Summary: Python module for Bonaventure temperature scale conversions
Home-page: https://github.com/whapoproject/bonaventure_scale
Author: Bonaventure
Author-email: niyibizibonaventure33@gmail.com
Classifier: Programming Language :: Python :: 3
Classifier: License :: OSI Approved :: MIT License
Classifier: Operating System :: OS Independent
Requires-Python: >=3.6
License-File: LICENSE
Dynamic: author
Dynamic: author-email
Dynamic: classifier
Dynamic: description
Dynamic: description-content-type
Dynamic: home-page
Dynamic: license-file
Dynamic: requires-python
Dynamic: summary
